client/__about__.py
client/__init__.py
client/auth.py
client/client.py
client/error.py
client/kv.py
client/lease.py
client/lock.py
client/maintenance.py
client/protocol.py
client/txn.py
client/watch.py
py_xline-0.1.0.dist-info/METADATA
py_xline-0.1.0.dist-info/WHEEL
py_xline-0.1.0.dist-info/licenses/LICENSE
py_xline-0.1.0.dist-info/RECORD
