Metadata-Version: 2.1
Name: py-xline
Version: 0.1.0
Summary: py-xline is an official xline client sdk, written in Python.
Project-URL: Documentation, https://github.com/xline-kv/py-xline#readme
Project-URL: Issues, https://github.com/xline-kv/py-xline/issues
Project-URL: Source, https://github.com/xline-kv/py-xline
Author-email: LingKa <cnfty786@gmail.com>
License-Expression: Apache-2.0
License-File: LICENSE
Classifier: Development Status :: 4 - Beta
Classifier: Programming Language :: Python
Classifier: Programming Language :: Python :: 3.7
Classifier: Programming Language :: Python :: 3.8
Classifier: Programming Language :: Python :: 3.9
Classifier: Programming Language :: Python :: 3.10
Classifier: Programming Language :: Python :: 3.11
Classifier: Programming Language :: Python :: Implementation :: CPython
Classifier: Programming Language :: Python :: Implementation :: PyPy
Requires-Python: >=3.7
Requires-Dist: grpcio-tools==1.58.0
Requires-Dist: grpcio==1.58.0
Requires-Dist: passlib
Requires-Dist: pytest-asyncio
